README.md
setup.py
PyROA/PyROA.py
PyROA/Utils.py
PyROA/__init__.py
PyROA.egg-info/PKG-INFO
PyROA.egg-info/SOURCES.txt
PyROA.egg-info/dependency_links.txt
PyROA.egg-info/top_level.txt