Metadata-Version: 2.1
Name: PyROA
Version: 3.2.1
Summary: PyROA is a tool for modelling quasar lightcurves
Home-page: https://github.com/FergusDonnan/PyROA
Author: Fergus Donnan,
Author-email: fergus.donnan@physics.ox.ac.uk
License: UNKNOWN
Platform: UNKNOWN
Classifier: Programming Language :: Python :: 3
Classifier: License :: OSI Approved :: MIT License
Classifier: Operating System :: OS Independent
